pygye/__init__.py
pygye/calculation.py
pygye-0.0.3.dist-info/licenses/LICENSE
pygye-0.0.3.dist-info/METADATA
pygye-0.0.3.dist-info/WHEEL
pygye-0.0.3.dist-info/top_level.txt
pygye-0.0.3.dist-info/RECORD
