Metadata-Version: 2.4
Name: pygye
Version: 0.0.3
Summary: A simple package for basic calculations like addition.
Author-email: Gokay Sahin <gokay285@gmail.com>
Project-URL: Homepage, https://github.com/gokaysahin/pygye
Keywords: calculation,math,pygye
Classifier: Development Status :: 3 - Alpha
Classifier: Intended Audience :: Developers
Classifier: License :: OSI Approved :: MIT License
Classifier: Programming Language :: Python :: 3
Classifier: Operating System :: OS Independent
Requires-Python: >=3.6
License-File: LICENSE
Dynamic: license-file
